libs/__init__.py
libs/iolib/__init__.py
libs/iolib/file.py
libs/iterlib/__init__.py
libs/ndjson/__init__.py
libs/tests/__init__.py
libs/tests/test_iolib.py
libs/tests/test_iterlib.py
libs/tests/test_ndjson.py
libs-0.0.10.dist-info/LICENSE
libs-0.0.10.dist-info/METADATA
libs-0.0.10.dist-info/WHEEL
libs-0.0.10.dist-info/top_level.txt
libs-0.0.10.dist-info/RECORD
