Metadata-Version: 2.1
Name: libs
Version: 0.0.10
Summary: Packages of tools
Home-page: https://github.com/phyng/libs
Author: phyng
Author-email: phyngk@gmail.com
License: UNKNOWN
Platform: UNKNOWN
Classifier: Operating System :: OS Independent
Classifier: Programming Language :: Python :: 3
Classifier: License :: OSI Approved :: MIT License
